oneclick/__init__.py
oneclick/base.py
oneclick/config.py
oneclick/config_original.py
oneclick/exceptions.py
oneclick/main.py
oneclick/runArg.py
oneclick/sendEmail.py
oneclick/setup.py
oneclick/test.py
oneclick/analysis/__init__.py
oneclick/analysis/aip_analysis.py
oneclick/analysis/analysis.py
oneclick/analysis/highlight_analysis.py
oneclick/analysis/runAnalysis.py
oneclick/analysis/trackAnalysis.py
oneclick/discovery/__init__.py
oneclick/discovery/cleanup.py
oneclick/discovery/cloc.py
oneclick/discovery/discoveryReport.py
oneclick/discovery/prep.py
oneclick/discovery/profiler.py
oneclick/discovery/sourceValidation.py
oneclick/discovery/sqlDiscovery.py
oneclick/discovery/unzip.py
com.castsoftware.uc.oneclick-1.1.3.dist-info/METADATA
com.castsoftware.uc.oneclick-1.1.3.dist-info/WHEEL
com.castsoftware.uc.oneclick-1.1.3.dist-info/top_level.txt
com.castsoftware.uc.oneclick-1.1.3.dist-info/RECORD
