Metadata-Version: 2.1
Name: com.castsoftware.uc.oneclick
Version: 1.1.3
Summary: AIP and Highlight Automation
Project-URL: Homepage, https://github.com/CAST-Extend/com.castsoftware.uc.arg
Project-URL: Bug Tracker, https://github.com/CAST-Extend/com.castsoftware.uc.arg/issues
Classifier: Programming Language :: Python :: 3
Classifier: License :: OSI Approved :: GNU General Public License v3 (GPLv3)
Classifier: Operating System :: OS Independent
Requires-Python: >=3.10
Requires-Dist: pandas
Requires-Dist: python-docx
Requires-Dist: argparse_formatter
Requires-Dist: django
Requires-Dist: pyunpack
Requires-Dist: tqdm
Requires-Dist: patool
Requires-Dist: archive
Requires-Dist: pypiwin32
Requires-Dist: psycopg2
Requires-Dist: openpyxl
Requires-Dist: com.castsoftware.uc.python.common>=1.1.14
